{
    "error": "", 
    "parkingSpots": [
        {
            "index": 0, 
            "name": 0, 
            "spots": [
                {
                    "x": 447, 
                    "y": 134
                }, 
                {
                    "x": 505, 
                    "y": 96
                }, 
                {
                    "x": 549, 
                    "y": 124
                }, 
                {
                    "x": 453, 
                    "y": 182
                }
            ]
        }, 
        {
            "index": 1, 
            "name": 1, 
            "spots": [
                {
                    "x": 261, 
                    "y": 60
                }, 
                {
                    "x": 374, 
                    "y": 139
                }, 
                {
                    "x": 363, 
                    "y": 88
                }, 
                {
                    "x": 295, 
                    "y": 41
                }
            ]
        }, 
        {
            "index": 5, 
            "name": 5, 
            "spots": [
                {
                    "x": 533, 
                    "y": 191
                }, 
                {
                    "x": 563, 
                    "y": 168
                }, 
                {
                    "x": 645, 
                    "y": 218
                }, 
                {
                    "x": 652, 
                    "y": 259
                }
            ]
        }, 
        {
            "index": 6, 
            "name": 6, 
            "spots": [
                {
                    "x": 733, 
                    "y": 263
                }, 
                {
                    "x": 808, 
                    "y": 203
                }, 
                {
                    "x": 766, 
                    "y": 176
                }, 
                {
                    "x": 717, 
                    "y": 215
                }
            ]
        }
    ]
}